xj_flow/__init__.py
xj_flow/admin.py
xj_flow/apps.py
xj_flow/models.py
xj_flow/service_register.py
xj_flow/urls.py
xj_flow/apis/__init__.py
xj_flow/apis/finish_flow_apis.py
xj_flow/apis/flow_action_list.py
xj_flow/apis/flow_apply_apis.py
xj_flow/apis/flow_list.py
xj_flow/apis/flow_node_list.py
xj_flow/apis/flow_node_rule_list.py
xj_flow/apis/flow_node_to_action_list.py
xj_flow/apis/flow_process.py
xj_flow/flow_middlewares/__init__.py
xj_flow/flow_middlewares/enroll_sms_notice.py
xj_flow/flow_middlewares/flow_middleware_base.py
xj_flow/migrations/0001_initial.py
xj_flow/migrations/__init__.py
xj_flow/services/__init__.py
xj_flow/services/flow_apply_service.py
xj_flow/services/flow_basic_service.py
xj_flow/services/flow_finish_flows.py
xj_flow/services/flow_process_service.py
xj_flow/utils/__init__.py
xj_flow/utils/check_type.py
xj_flow/utils/custom_response.py
xj_flow/utils/custom_tool.py
xj_flow/utils/digit_algorithm.py
xj_flow/utils/excel_operate.py
xj_flow/utils/file_operate.py
xj_flow/utils/j_config.py
xj_flow/utils/j_dict.py
xj_flow/utils/j_valuation.py
xj_flow/utils/join_list.py
xj_flow/utils/request_params_wrapper.py
xj_flow/utils/service_manager.py
xj_flow/utils/user_wrapper.py
xj_flow/utils/validate.py
xj_flow-1.0.28.dist-info/METADATA
xj_flow-1.0.28.dist-info/WHEEL
xj_flow-1.0.28.dist-info/top_level.txt
xj_flow-1.0.28.dist-info/RECORD
