Metadata-Version: 2.1
Name: xj-flow
Version: 1.0.28
Summary: 流程模块
Author: 赵向明
Author-email: sieyoo@163.com
Maintainer: 孙楷炎
Maintainer-email: sky4834@163.com
License: apache 3.0
